claude2_api/__init__.py
claude2_api/client.py
claude2_api/errors.py
claude2_api/session.py
unofficial_claude2_api-0.3.0.dist-info/LICENSE
unofficial_claude2_api-0.3.0.dist-info/METADATA
unofficial_claude2_api-0.3.0.dist-info/WHEEL
unofficial_claude2_api-0.3.0.dist-info/top_level.txt
unofficial_claude2_api-0.3.0.dist-info/RECORD
