Metadata-Version: 2.1
Name: unofficial-claude2-api
Version: 0.3.0
Summary: Unofficial Claude2 API supporting direct HTTP chat creation/deletion/retrieval, multiple message attachments, proxies and auto session gathering using Firefox with geckodriver. 
Home-page: https://github.com/st1vms/unofficial-claude2-api
Author: st1vms
Author-email: stefano.maria.salvatore@gmail.com
Classifier: Programming Language :: Python :: 3.10
Classifier: License :: OSI Approved :: MIT License
Classifier: Operating System :: OS Independent
Requires-Python: >=3.10
License-File: LICENSE
Requires-Dist: requests
Requires-Dist: selgym
Requires-Dist: curl-cffi
Requires-Dist: tzlocal
Requires-Dist: brotli
